neumai/Chunkers/CharacterChunker.py
neumai/Chunkers/Chunker.py
neumai/Chunkers/ChunkerEnum.py
neumai/Chunkers/CustomChunker.py
neumai/Chunkers/RecursiveChunker.py
neumai/Chunkers/__init__.py
neumai/Client/NeumClient.py
neumai/Client/__init__.py
neumai/DataConnectors/AzureBlobConnector.py
neumai/DataConnectors/DataConnector.py
neumai/DataConnectors/DataConnectorEnum.py
neumai/DataConnectors/FileConnector.py
neumai/DataConnectors/PostgresConnector.py
neumai/DataConnectors/S3Connector.py
neumai/DataConnectors/SharepointConnector.py
neumai/DataConnectors/SingleStoreConnector.py
neumai/DataConnectors/SupabaseStorageConnector.py
neumai/DataConnectors/WebsiteConnector.py
neumai/DataConnectors/__init__.py
neumai/EmbedConnectors/AzureOpenAIEmbed.py
neumai/EmbedConnectors/EmbedConnector.py
neumai/EmbedConnectors/EmbedConnectorEnum.py
neumai/EmbedConnectors/HuggingFaceEmbed.py
neumai/EmbedConnectors/OpenAIEmbed.py
neumai/EmbedConnectors/ReplicateEmbed.py
neumai/EmbedConnectors/__init__.py
neumai/Loaders/AutoLoader.py
neumai/Loaders/CSVLoader.py
neumai/Loaders/HTMLLoader.py
neumai/Loaders/JSONLoader.py
neumai/Loaders/Loader.py
neumai/Loaders/LoaderEnum.py
neumai/Loaders/LoaderHelper.py
neumai/Loaders/MarkdownLoader.py
neumai/Loaders/PDFLoader.py
neumai/Loaders/__init__.py
neumai/ModelFactories/ChunkerFactory.py
neumai/ModelFactories/DataConnectorFactory.py
neumai/ModelFactories/EmbedConnectorFactory.py
neumai/ModelFactories/LoaderFactory.py
neumai/ModelFactories/SinkConnectorFactory.py
neumai/ModelFactories/__init__.py
neumai/Pipelines/Pipeline.py
neumai/Pipelines/PipelineRun.py
neumai/Pipelines/TriggerSchedule.py
neumai/Pipelines/TriggerSyncTypeEnum.py
neumai/Pipelines/__init__.py
neumai/Shared/CloudFile.py
neumai/Shared/Exceptions/__init__.py
neumai/Shared/LocalFile.py
neumai/Shared/NeumDocument.py
neumai/Shared/NeumSearch.py
neumai/Shared/NeumSinkInfo.py
neumai/Shared/NeumVector.py
neumai/Shared/Selector.py
neumai/Shared/__init__.py
neumai/SinkConnectors/LanceDBSink.py
neumai-0.0.40.dist-info/METADATA
neumai-0.0.40.dist-info/WHEEL
neumai-0.0.40.dist-info/RECORD
