Metadata-Version: 2.1
Name: neumai
Version: 0.0.40
Summary: Package containing connectors for Neum AI.
Home-page: https://neum.ai
License: MIT
Keywords: neumai,ai tools,data tools
Author: David de Matheu
Author-email: david@tryneum.com
Requires-Python: >=3.10,<4.0
Classifier: License :: OSI Approved :: MIT License
Classifier: Programming Language :: Python :: 3
Classifier: Programming Language :: Python :: 3.10
Classifier: Programming Language :: Python :: 3.11
Requires-Dist: azure-identity (==1.15.0)
Requires-Dist: azure-storage-blob (==12.19.0)
Requires-Dist: beautifulsoup4 (==4.12.2)
Requires-Dist: boto3 (==1.28.81)
Requires-Dist: fastapi (>0.98.0)
Requires-Dist: lancedb (==0.3.6)
Requires-Dist: langchain (==0.0.335)
Requires-Dist: marqo (==2.1.0)
Requires-Dist: openai (==1.2.4)
Requires-Dist: pandas (==2.1.0)
Requires-Dist: pinecone-client (==2.2.2)
Requires-Dist: pydantic (==1.10.13)
Requires-Dist: pylance (==0.8.21)
Requires-Dist: pypdf (==3.9.1)
Requires-Dist: qdrant_client (==1.6.9)
Requires-Dist: replicate (==0.13.0)
Requires-Dist: requests (==2.31.0)
Requires-Dist: scikit-learn (==1.2.2)
Requires-Dist: scipy (==1.10.1)
Requires-Dist: singlestoredb (==0.9.1)
Requires-Dist: starlette (==0.27.0)
Requires-Dist: supabase (==2.0.3)
Requires-Dist: tiktoken (==0.4.0)
Requires-Dist: tokenizers (==0.13.2)
Requires-Dist: transformers (==4.27.3)
Requires-Dist: unstructured (==0.7.7)
Requires-Dist: vecs (==0.4.2)
Requires-Dist: weaviate-client (==3.25.3)
Project-URL: Repository, https://github.com/NeumTry/NeumAI
